alist_mikananirss/__init__.py
alist_mikananirss/__main__.py
alist_mikananirss/main.py
alist_mikananirss/alist/__init__.py
alist_mikananirss/alist/api.py
alist_mikananirss/alist/tasks.py
alist_mikananirss/bot/__init__.py
alist_mikananirss/bot/bot_base.py
alist_mikananirss/bot/notificationbot.py
alist_mikananirss/bot/pushplus_bot.py
alist_mikananirss/bot/tgbot.py
alist_mikananirss/common/__init__.py
alist_mikananirss/common/database.py
alist_mikananirss/common/config/__init__.py
alist_mikananirss/common/config/basic.py
alist_mikananirss/common/config/bot_assistant.py
alist_mikananirss/common/config/config.py
alist_mikananirss/common/config/extractor.py
alist_mikananirss/common/config/notifier.py
alist_mikananirss/common/config/remap.py
alist_mikananirss/core/__init__.py
alist_mikananirss/core/bot_assistant.py
alist_mikananirss/core/download_manager.py
alist_mikananirss/core/filter.py
alist_mikananirss/core/notification_sender.py
alist_mikananirss/core/remapper.py
alist_mikananirss/core/renamer.py
alist_mikananirss/core/rss_monitor.py
alist_mikananirss/extractor/__init__.py
alist_mikananirss/extractor/base.py
alist_mikananirss/extractor/extractor.py
alist_mikananirss/extractor/llm_extractor.py
alist_mikananirss/extractor/models.py
alist_mikananirss/extractor/regex.py
alist_mikananirss/extractor/llm/__init__.py
alist_mikananirss/extractor/llm/base.py
alist_mikananirss/extractor/llm/deepseek.py
alist_mikananirss/extractor/llm/google.py
alist_mikananirss/extractor/llm/openai.py
alist_mikananirss/extractor/llm/prompt/__init__.py
alist_mikananirss/extractor/llm/prompt/prompt.py
alist_mikananirss/extractor/llm/prompt/json_object/anime_name.txt
alist_mikananirss/extractor/llm/prompt/json_object/resource_title.txt
alist_mikananirss/extractor/llm/prompt/json_object/tmdb_find_anime.txt
alist_mikananirss/extractor/llm/prompt/json_object/tmdb_retry_search.txt
alist_mikananirss/extractor/llm/prompt/json_object/tmdb_search_param.txt
alist_mikananirss-0.5.5.dist-info/METADATA
alist_mikananirss-0.5.5.dist-info/WHEEL
alist_mikananirss-0.5.5.dist-info/entry_points.txt
alist_mikananirss-0.5.5.dist-info/RECORD
