Metadata-Version: 2.4
Name: alist-mikananirss
Version: 0.5.5
Summary: Automatically fetch anime updates from the Mikan Project's RSS feed and offline download them to the cloud drive through Alist.
Requires-Python: >=3.11
Requires-Dist: aiohttp>=3.11
Requires-Dist: aiosqlite>=0.20.0
Requires-Dist: async-lru>=2.0.4
Requires-Dist: asyncio>=3.4.3
Requires-Dist: beautifulsoup4>=4.12.3
Requires-Dist: feedparser>=6.0.11
Requires-Dist: google-genai>=1.10.0
Requires-Dist: loguru>=0.7.3
Requires-Dist: openai>=1.58.1
Requires-Dist: python-telegram-bot>=21.9
Requires-Dist: pyyaml>=6.0.2
Requires-Dist: tenacity>=9.0.0
